sxm_discord/__init__.py
sxm_discord/bot.py
sxm_discord/checks.py
sxm_discord/converters.py
sxm_discord/models.py
sxm_discord/music.py
sxm_discord/player.py
sxm_discord/sxm.py
sxm_discord/utils.py
sxm_discord-0.2.5.dist-info/LICENSE
sxm_discord-0.2.5.dist-info/WHEEL
sxm_discord-0.2.5.dist-info/METADATA
sxm_discord-0.2.5.dist-info/RECORD
