Metadata-Version: 2.1
Name: sxm_discord
Version: 0.2.5
Summary: Top-level package for sxm-discord.
Home-page: https://github.com/AngellusMortis/sxm-discord
License: MIT license
Keywords: sxm,SiriusXM,XM Radio,Discord
Author: Christopher Bailey
Author-email: cbailey@mort.is
Requires-Python: >=3.7
Classifier: Development Status :: 4 - Beta
Classifier: Intended Audience :: Developers
Classifier: License :: OSI Approved :: MIT License
Classifier: Natural Language :: English
Classifier: Programming Language :: Python :: 3
Classifier: Programming Language :: Python :: 3.7
Classifier: Programming Language :: Python :: 3.8
Classifier: Programming Language :: Python :: 3.9
Requires-Dist: discord.py[voice]
Requires-Dist: discord-py-slash-command
Requires-Dist: humanize
Requires-Dist: sxm-player>=0.2.1
Requires-Dist: pydantic
Requires-Dist: tabulate
Requires-Dist: bandit ; extra == "dev"
Requires-Dist: black ; extra == "dev"
Requires-Dist: discord.py-stubs ; extra == "dev"
Requires-Dist: flake8-bugbear ; extra == "dev"
Requires-Dist: flake8-builtins ; extra == "dev"
Requires-Dist: flake8-commas ; extra == "dev"
Requires-Dist: flake8-comprehensions ; extra == "dev"
Requires-Dist: flake8 ; extra == "dev"
Requires-Dist: flit ; extra == "dev"
Requires-Dist: isort ; extra == "dev"
Requires-Dist: mypy ; extra == "dev"
Requires-Dist: pip-tools ; extra == "dev"
Requires-Dist: pylint ; extra == "dev"
Requires-Dist: pyproject-flake8 ; extra == "dev"
Requires-Dist: rstcheck ; extra == "dev"
Requires-Dist: sqlalchemy-stubs ; extra == "dev"
Requires-Dist: types-click ; extra == "dev"
Requires-Dist: types-psutil ; extra == "dev"
Requires-Dist: types-PyYAML ; extra == "dev"
Requires-Dist: typing-extensions~=3.7.4.1 ; extra == "dev"
Requires-Dist: types-tabulate ; extra == "dev"
Requires-Dist: furo ; extra == "doc"
Requires-Dist: snooty-lextudio ; extra == "doc"
Requires-Dist: sphinx ; extra == "doc"
Requires-Dist: pytest ; extra == "test"
Requires-Dist: pytest-cov ; extra == "test"
Requires-Dist: pytest-socket ; extra == "test"
Requires-Dist: pytest-sugar ; extra == "test"
Requires-Dist: pytest-clarity ; extra == "test"
Requires-Dist: tox ; extra == "test"
Requires-Dist: coverage ; extra == "test"
Project-URL: Documentation, https://sxm-discord.readthedocs.io/en/latest/
Provides-Extra: dev
Provides-Extra: doc
Provides-Extra: test
